Metadata-Version: 2.4
Name: hmt-dependency-injector
Version: 4.48.3
Summary: Dependency injection framework for Python
Author-email: Donq Lee <dev@donql.net>
Maintainer-email: Donq Lee <dev@donql.net>
License: Copyright (c) 2024, Roman Mogylatov
Project-URL: Homepage, https://github.com/ets-labs/python-dependency-injector
Project-URL: Documentation, https://python-dependency-injector.ets-labs.org/
Project-URL: Download, https://pypi.python.org/pypi/dependency_injector
Keywords: Dependency injection,DI,Inversion of Control,PoH,Factory,Singleton,Design patterns,Flask
Classifier: Development Status :: 5 - Production/Stable
Classifier: Intended Audience :: Developers
Classifier: License :: OSI Approved :: BSD License
Classifier: Operating System :: OS Independent
Classifier: Programming Language :: Python
Classifier: Programming Language :: Python :: 3
Classifier: Programming Language :: Python :: 3.8
Classifier: Programming Language :: Python :: 3.9
Classifier: Programming Language :: Python :: 3.10
Classifier: Programming Language :: Python :: 3.11
Classifier: Programming Language :: Python :: 3.12
Classifier: Programming Language :: Python :: 3.13
Classifier: Programming Language :: Python :: Implementation :: CPython
Classifier: Programming Language :: Python :: Implementation :: PyPy
Classifier: Framework :: AsyncIO
Classifier: Framework :: Bottle
Classifier: Framework :: Django
Classifier: Framework :: Flask
Classifier: Framework :: Pylons
Classifier: Framework :: Pyramid
Classifier: Framework :: Pytest
Classifier: Framework :: TurboGears
Classifier: Topic :: Software Development
Classifier: Topic :: Software Development :: Libraries
Classifier: Topic :: Software Development :: Libraries :: Python Modules
Requires-Python: >=3.8
License-File: LICENSE.rst
Requires-Dist: typing-extensions; python_version < "3.13"
Provides-Extra: yaml
Requires-Dist: pyyaml; extra == "yaml"
Provides-Extra: pydantic
Requires-Dist: pydantic; extra == "pydantic"
Provides-Extra: pydantic2
Requires-Dist: pydantic-settings; extra == "pydantic2"
Provides-Extra: flask
Requires-Dist: flask; extra == "flask"
Provides-Extra: aiohttp
Requires-Dist: aiohttp; extra == "aiohttp"
Dynamic: license-file
